CHANGES.txt
DEPENDENCIES.txt
README.txt
bootstrap.py
buildout.cfg
setup.py
src/ks/__init__.py
src/ks.smartimage.egg-info/PKG-INFO
src/ks.smartimage.egg-info/SOURCES.txt
src/ks.smartimage.egg-info/dependency_links.txt
src/ks.smartimage.egg-info/namespace_packages.txt
src/ks.smartimage.egg-info/not-zip-safe
src/ks.smartimage.egg-info/requires.txt
src/ks.smartimage.egg-info/top_level.txt
src/ks/smartimage/CHANGES.txt
src/ks/smartimage/TODO.txt
src/ks/smartimage/__init__.py
src/ks/smartimage/configure.zcml
src/ks/smartimage/interfaces.py
src/ks/smartimage/smartimage.py
src/ks/smartimage/smartimage_doc.txt
src/ks/smartimage/smartimage_sample.pt
src/ks/smartimage/smartimage_sample_eval.pt
src/ks/smartimage/browser/__init__.py
src/ks/smartimage/browser/configure.zcml
src/ks/smartimage/browser/scale_error.pt
src/ks/smartimage/etc/smartimage-configure.zcml
src/ks/smartimage/locales/en/LC_MESSAGES/ks.smartimage.po
src/ks/smartimage/locales/ru/LC_MESSAGES/ks.smartimage.mo
src/ks/smartimage/locales/ru/LC_MESSAGES/ks.smartimage.po
src/ks/smartimage/smartimageadapter/__init__.py
src/ks/smartimage/smartimageadapter/configure.zcml
src/ks/smartimage/smartimageadapter/interfaces.py
src/ks/smartimage/smartimageadapter/scale.py
src/ks/smartimage/smartimageadapter/smartimageadapter.py
src/ks/smartimage/smartimageadapter/smartimagebyid.py
src/ks/smartimage/smartimageadapter/smartimagecached.py
src/ks/smartimage/smartimageadapter/smartimagecontainer.py
src/ks/smartimage/smartimagecache/__init__.py
src/ks/smartimage/smartimagecache/configure.zcml
src/ks/smartimage/smartimagecache/interfaces.py
src/ks/smartimage/smartimagecache/resamplevocabulary.py
src/ks/smartimage/smartimagecache/scale.py
src/ks/smartimage/smartimagecache/scalevocabulary.py
src/ks/smartimage/smartimagecache/smartimagecache.py
src/ks/smartimage/smartimagecache/smartimagecache.txt
src/ks/smartimage/smartimagecache/widgets.py
src/ks/smartimage/smartimagecache/browser/__init__.py
src/ks/smartimage/smartimagecache/browser/configure.zcml
src/ks/smartimage/smartimagecache/browser/stat.pt
src/ks/smartimage/smartimagecache/browser/view.py
src/ks/smartimage/smartimagehandler/__init__.py
src/ks/smartimage/smartimagehandler/configure.zcml
src/ks/smartimage/smartimagehandler/smartimagehandler.py
