Metadata-Version: 1.0
Name: ks.smartimage
Version: 1.2.2
Summary: Efficiently store and publish images with ks.smartimage
Home-page: http://code.keysolutionscorp.com/downloads/public/pypi/ks.smartimage
Author: Key Solutions Development TEAM
Author-email: ksd-team@keysolutions.ru
License: ZPL 2.1
Platform: UNKNOWN
Classifier: Intended Audience :: Developers
Classifier: License :: OSI Approved :: Zope Public License
Classifier: Programming Language :: Python
Classifier: Natural Language :: English
Classifier: Operating System :: OS Independent
Classifier: Topic :: Internet :: WWW/HTTP
Classifier: Topic :: Software Development
Classifier: Framework :: Zope3
